rxhands/__init__.py
rxhands/auxiliary.py
rxhands/clustering.py
rxhands/cut_img.py
rxhands/dataset.py
rxhands/edges.py
rxhands/entrypoints.py
rxhands/geometry.py
rxhands/haar_classification.py
rxhands/hand_model.py
rxhands/main.py
rxhands/neural_model.py
rxhands/preprocessing.py
rxhands/ridge.py
rxhands/segmentation.py
rxhands/superpixels.py
rxhands/svc_classification.py
rxhands/bin/clf.bin
rxhands/bin/selected_img_names.bin
rxhands_unam_colab-0.25.dist-info/LICENSE
rxhands_unam_colab-0.25.dist-info/METADATA
rxhands_unam_colab-0.25.dist-info/WHEEL
rxhands_unam_colab-0.25.dist-info/entry_points.txt
rxhands_unam_colab-0.25.dist-info/top_level.txt
rxhands_unam_colab-0.25.dist-info/RECORD
