Metadata-Version: 2.1
Name: rxhands-unam-colab
Version: 0.25
Summary: Labeling of finger landmarks in hand xrays.
Home-page: https://github.com/elmugrearturo/rxhands
Author: Arturo Curiel
Author-email: me@arturocuriel.com
Classifier: Programming Language :: Python :: 3
Classifier: License :: OSI Approved :: MIT License
Classifier: Operating System :: OS Independent
License-File: LICENSE
Requires-Dist: wheel <=0.43.0
Requires-Dist: numpy <=1.26.4
Requires-Dist: matplotlib <=3.9.0
Requires-Dist: opencv-python <=4.9.0.80
Requires-Dist: pandas <=2.2.2
Requires-Dist: scikit-image <=0.23.2
Requires-Dist: scikit-learn <=1.5.0
Requires-Dist: tensorflow <=2.16.1
